README.md
setup.py
rpi_d3m_primitives/JMIplus_auto.py
rpi_d3m_primitives/S2TMBplus.py
rpi_d3m_primitives/STMBplus_auto.py
rpi_d3m_primitives/TreeAugmentedNB_BayesianInf.py
rpi_d3m_primitives/__init__.py
rpi_d3m_primitives.egg-info/PKG-INFO
rpi_d3m_primitives.egg-info/SOURCES.txt
rpi_d3m_primitives.egg-info/dependency_links.txt
rpi_d3m_primitives.egg-info/entry_points.txt
rpi_d3m_primitives.egg-info/requires.txt
rpi_d3m_primitives.egg-info/top_level.txt
rpi_d3m_primitives/featSelect/Feature_Selector_model.py
rpi_d3m_primitives/featSelect/HypothesisTest.py
rpi_d3m_primitives/featSelect/JMIplus.py
rpi_d3m_primitives/featSelect/JMIplus_auto.py
rpi_d3m_primitives/featSelect/JointMutualInformation.py
rpi_d3m_primitives/featSelect/Keyi_RecognizePC_adaptive_soft.py
rpi_d3m_primitives/featSelect/Keyi_STMB_Adaptive_soft.py
rpi_d3m_primitives/featSelect/Keyi_checkDatasize.py
rpi_d3m_primitives/featSelect/Large_Scale_IPCMB.py
rpi_d3m_primitives/featSelect/Large_Scale_STMB.py
rpi_d3m_primitives/featSelect/MI_IndependenceTest.py
rpi_d3m_primitives/featSelect/MergeArrays.py
rpi_d3m_primitives/featSelect/NaiveBayes_BayesianInf.py
rpi_d3m_primitives/featSelect/NaiveBayes_PointInf.py
rpi_d3m_primitives/featSelect/Predictor.py
rpi_d3m_primitives/featSelect/RecognizePC_BayesFactor.py
rpi_d3m_primitives/featSelect/RecognizePC_Gtest.py
rpi_d3m_primitives/featSelect/RelationSet.py
rpi_d3m_primitives/featSelect/S2TMBplus.py
rpi_d3m_primitives/featSelect/STMB_BayesFactor.py
rpi_d3m_primitives/featSelect/STMB_G_test.py
rpi_d3m_primitives/featSelect/STMBplus_auto.py
rpi_d3m_primitives/featSelect/ScoreCache.py
rpi_d3m_primitives/featSelect/__init__.py
rpi_d3m_primitives/featSelect/adaptiveMI.py
rpi_d3m_primitives/featSelect/adaptivePartitioning.py
rpi_d3m_primitives/featSelect/combineJointDist.py
rpi_d3m_primitives/featSelect/conditionalMI.py
rpi_d3m_primitives/featSelect/discretization.py
rpi_d3m_primitives/featSelect/findPC.py
rpi_d3m_primitives/featSelect/helperFunctions.py
rpi_d3m_primitives/featSelect/informationTheoreticFunctions.py
rpi_d3m_primitives/featSelect/mutualInformation.py
rpi_d3m_primitives/featSelect/profiler.py
rpi_d3m_primitives/featSelect/sSTMB.py
rpi_d3m_primitives/featSelect/scoreLearning.py
